{
    "1": "Ste synmi P\u00e1na, svojho Boha: nerobte si z\u00e1rezy, ani si nestrihajte vlasy medzi o\u010dami pre m\u0155tveho;",
    "2": "ve\u010f ty si \u013eud, zasv\u00e4ten\u00fd P\u00e1novi, svojmu Bohu, a on si \u0165a vyvolil spomedzi v\u0161etk\u00fdch n\u00e1rodov, ktor\u00e9 s\u00fa na zemi, aby si bol jeho vlastn\u00fdm \u013eudom. -",
    "3": "Nejedzte ni\u010d ne\u010dist\u00e9!",
    "4": "Toto s\u00fa zvierat\u00e1, ktor\u00e9 m\u00f4\u017eete jes\u0165: b\u00fdka, ovcu, kozu,",
    "5": "jele\u0148a, gazelu, kozoro\u017eca, antilopu, byvola a \u017eirafu.",
    "6": "Jedzte v\u0161etky zvierat\u00e1, ktor\u00e9 pre\u017e\u00favaj\u00fa a maj\u00fa rozdelen\u00e9 kopyt\u00e1 na dvoje.",
    "7": "Ale tie, \u010do pre\u017e\u00favaj\u00fa a nemaj\u00fa rozdelen\u00e9 kopyt\u00e1 na dvoje, nesmiete jes\u0165, ako: \u0165avu, zajaca a jazveca; s\u00fa to s\u00edce pre\u017e\u00favavce, ale nemaj\u00fa rozdvojen\u00e9 papr\u010dky, s\u00fa pre v\u00e1s ne\u010dist\u00e9;",
    "8": "aj svi\u0148a, ktor\u00e1 s\u00edce m\u00e1 rozdvojen\u00e9 papr\u010dky, ale nepre\u017e\u00fava, je pre v\u00e1s ne\u010dist\u00e1 - ich m\u00e4so nesmiete jes\u0165 a ich zdochl\u00edn sa nedot\u00fdkajte!",
    "9": "Toto budete jes\u0165 zo v\u0161etk\u00e9ho, \u010do \u017eije vo vod\u00e1ch: \u010do m\u00e1 plutvy a \u0161upiny, m\u00f4\u017eete jes\u0165.",
    "10": "Ale z toho, \u010do nem\u00e1 plutvy a \u0161upiny, nesmiete jes\u0165 ni\u010d, to je pre v\u00e1s ne\u010dist\u00e9.",
    "11": "Jedzte v\u0161etky \u010dist\u00e9 vt\u00e1ky;",
    "12": "tieto v\u0161ak nejedzte: orla, orlosupa, orlosupa bradat\u00e9ho,",
    "13": "ka\u0148u, sokola a v\u0161etky druhy jastrabov,",
    "14": "v\u0161etky druhy krkavcov,",
    "15": "p\u0161trosa, kuku\u010dku, \u010dajku a krahulce v\u0161etk\u00fdch druhov,",
    "16": "bociana, labu\u0165, ibisa,",
    "17": "kormor\u00e1na, volavku, bu\u010diaka,",
    "18": "pelik\u00e1na, kuviky ka\u017ed\u00e9ho druhu, dudka a netopiera.",
    "19": "Aj v\u0161etko, \u010do sa plaz\u00ed a m\u00e1 kr\u00eddla, je pre v\u00e1s ne\u010dist\u00e9 a nesmie sa jes\u0165!",
    "20": "\u010co je \u010dist\u00e9, m\u00f4\u017eete jes\u0165 v\u0161etko.",
    "21": "\u010coko\u013evek zdochlo, nejedzte! Daj to cudzincovi, \u010do b\u00fdva v tvojom bydlisku, nech to zje, lebo ty si \u013eud zasv\u00e4ten\u00fd P\u00e1novi, svojmu Bohu. -",
    "22": "Odde\u013e desiatu \u010diastku zo v\u0161etk\u00fdch svojich plod\u00edn, ktor\u00e9 ka\u017edoro\u010dne rod\u00ed zem,",
    "23": "a jedz to pred tv\u00e1rou P\u00e1na, svojho Boha, na mieste, ktor\u00e9 si vyvol\u00ed, aby sa na \u0148om vz\u00fdvalo jeho meno - teda desiatu \u010diastku zo svojho obilia, mu\u0161tu a oleja a prvoroden\u00e9 zo svojho dobytka a zo svojich oviec, aby si sa nau\u010dil b\u00e1\u0165 sa P\u00e1na, svojho Boha, v ka\u017ed\u00fd &#269;as.",
    "24": "Keby ti bola cesta pridlh\u00e1 a miesto, ktor\u00e9 si vyvol\u00ed P\u00e1n, tvoj Boh, aby tam b\u00fdval, ve\u013emi vzdialen\u00e9 od teba a ak \u0165a po\u017eehn\u00e1, nebude\u0161 mu m\u00f4c\u0165 donies\u0165 tieto veci,",
    "25": "pred\u00e1\u0161 to za peniaze, peniaze vezme\u0161 do hrsti a p\u00f4jde\u0161 na miesto, ktor\u00e9 si vyvolil P\u00e1n, tvoj Boh.",
    "26": "Za tie peniaze k\u00fap, \u010do sa ti \u017eiada: hov\u00e4dz\u00ed dobytok, ovce, v\u00edno a in\u00fd n\u00e1poj a v\u0161etko, \u010do sa ti za\u017eiada: a bude\u0161 to jes\u0165 pred P\u00e1nom, svoj\u00edm Bohom, bude\u0161 sa hosti\u0165 ty i tvoj dom,",
    "27": "aj levita, ktor\u00fd je v tvojom bydlisku; nezabudni na\u0148, lebo nem\u00e1 in\u00e9ho podielu na tvojom majetku.",
    "28": "Ka\u017ed\u00fd tret\u00ed rok oddel\u00ed\u0161 in\u00fa desiatu \u010das\u0165 zo v\u0161etkej \u00farody toho \u010dasu a nech\u00e1\u0161 ju vo svojom bydlisku.",
    "29": "Potom pr\u00edde levita, ktor\u00fd nem\u00e1 podiel ani dedi\u010dstvo ako ty, cudzinec, sirota a vdova, ktor\u00ed s\u00fa v tvojom bydlisku, nech sa najedia a nas\u00fdtia, aby \u0165a P\u00e1n, tvoj Boh, po\u017eehnal v ka\u017edej pr\u00e1ci tvojich r\u00fak, ktor\u00fa bude\u0161 kona\u0165."
}