{
    "1": "Rodokme\u0148 Je\u017ei\u0161a Krista, syna D\u00e1vidovho, syna Abrah\u00e1movho.",
    "2": "Abrah\u00e1m mal syna Iz\u00e1ka, Iz\u00e1k Jakuba, Jakub J\u00fadu a jeho bratov,",
    "3": "J\u00fada Faresa a Z\u00e1ru z Tamary. Fares mal syna Ezroma, Ezrom Arama.",
    "4": "Aram mal syna Aminadaba, Aminadab N\u00e1sona, N\u00e1son Salmona,",
    "5": "Salmon mal syna B\u00f3za z Rachaby, B\u00f3z Obeda z R\u00fat. Obed Jesseho",
    "6": "a Jesse kr\u00e1\u013ea D\u00e1vida. D\u00e1vid mal syna \u0160alam\u00fana z Uri\u00e1\u0161ovej \u017eeny.",
    "7": "\u0160alam\u00fan mal syna Roboama, Roboam Abi\u00e1\u0161a, Abi\u00e1\u0161 Azu,",
    "8": "Aza Jozafata, Jozafat Jorama, Joram Ozi\u00e1\u0161a.",
    "9": "Ozi\u00e1\u0161 mal syna Joatama, Joatam Achaza, Achaz Ezechi\u00e1\u0161a.",
    "10": "Ezechi\u00e1\u0161 mal syna Manassesa, Manasses Amona, Amon Jozi\u00e1\u0161a,",
    "11": "Jozi\u00e1\u0161 Jechoni\u00e1\u0161a a jeho bratov za babylonsk\u00e9ho zajatia.",
    "12": "Po babylonskom zajat\u00ed Jechoni\u00e1\u0161 mal syna Salatiela, Salatiel Zorob\u00e1bela,",
    "13": "Zorob\u00e1bel Abiuda, Abiud Eliakima, Eliakim Azora.",
    "14": "Azor mal syna Sadoka, Sadok Achima, Achim Eliuda.",
    "15": "Eliud mal syna Eleazara, Eleazar Matana, Matan Jakuba.",
    "16": "Jakub mal syna Jozefa, man\u017eela M\u00e1rie z ktorej sa narodil Je\u017ei\u0161, naz\u00fdvan\u00fd Kristus.",
    "17": "V\u0161etk\u00fdch pokolen\u00ed od Abrah\u00e1ma po D\u00e1vida bolo \u0161trn\u00e1s\u0165, od D\u00e1vida po babylonsk\u00e9 zajatie \u0161trn\u00e1s\u0165 a \u0161trn\u00e1s\u0165 od babylonsk\u00e9ho zajatia po Krista.",
    "18": "S naroden\u00edm Je\u017ei\u0161a Krista to bolo takto: Jeho matka M\u00e1ria bola zasn\u00faben\u00e1 s Jozefom: Ale sk\u00f4r, ako by boli za\u010dali spolu b\u00fdva\u0165, uk\u00e1zalo sa, \u017ee po\u010dala z Ducha Sv\u00e4t\u00e9ho.",
    "19": "Jozef, jej man\u017eel, bol \u010dlovek spravodliv\u00fd a nechcel ju vystavi\u0165 potupe, preto ju zam\u00fd\u0161\u013eal potajomky prepusti\u0165.",
    "20": "Ako o tom uva\u017eoval, zjavil sa mu vo sne P\u00e1nov anjel a povedal: \"Jozef, syn D\u00e1vidov, neboj sa prija\u0165 M\u00e1riu, svoju man\u017eelku, lebo to, \u010do sa v nej po\u010dalo, je z Ducha Sv\u00e4t\u00e9ho.",
    "21": "Porod\u00ed syna a d\u00e1\u0161 mu meno Je\u017ei\u0161, lebo on vyslobod\u00ed svoj \u013eud z hriechov.\"",
    "22": "To v\u0161etko sa stalo, aby sa splnilo, \u010do P\u00e1n povedal \u00fastami proroka:",
    "23": "\"H\u013ea, panna po\u010dne a porod\u00ed syna a daj\u00fa mu meno Emanuel,\" \u010do v preklade znamen\u00e1: Boh s nami.",
    "24": "Ke\u010f sa Jozef prebudil, urobil, ako mu prik\u00e1zal P\u00e1nov anjel, a prijal svoju man\u017eelku.",
    "25": "Ale nepoznal ju, k\u00fdm neporodila syna; a dal mu meno Je\u017ei\u0161."
}