{
    "1": "Ak sa obr\u00e1ti\u0161, Izrael, hovor\u00ed P\u00e1n, vr\u00e1\u0165 sa ku mne! A ak odstr\u00e1ni\u0161 spredo m\u0148a svoje ohavy, nebude\u0161 viac bl\u00fadi\u0165.",
    "2": "Vtedy bude\u0161 prisaha\u0165: \"Ako \u017eije P\u00e1n!\" poctivo, pravdivo a spravodlivo.\" V \u0148om sa bud\u00fa \u017eehna\u0165 n\u00e1rody a v \u0148om sa bud\u00fa chv\u00e1li\u0165.",
    "3": "Lebo takto hovor\u00ed P\u00e1n mu\u017eom J\u00fadska a Jeruzalema: \"Preorte si \u00fahor a nesejte do t\u0155nia!",
    "4": "Obre\u017ete sa P\u00e1novi, odstr\u00e1\u0148te predko\u017eku svojho srdca, mu\u017eovia J\u00fadska a obyvatelia Jeruzalema, in\u00e1\u010d vy\u0161\u013eahne s\u0165a plame\u0148 m\u00f4j hnev a bude horie\u0165 neuhasite\u013ene pre zlobu va\u0161ich skutkov.",
    "5": "Ozn\u00e1mte v J\u00fadsku, rozhl\u00e1ste v Jeruzaleme a povedzte, zahlaho\u013ete v krajine na tr\u00faby, volajte naplno a hovorte: \"Zrazte sa, p\u00f4jdeme do opevnen\u00fdch miest!\"",
    "6": "Hore so z\u00e1stavou, na Sion, utekajte a nezastavujte sa! Lebo od severu privediem ne\u0161\u0165astie a d\u00f4kladn\u00e9 zr\u00fatenie.",
    "7": "Vyst\u00fapil lev zo svojej h\u00fa\u0161tiny, vyrazil ni\u010dite\u013e n\u00e1rodov, vy\u0161iel zo svojho le\u017eiska, aby z tvojej krajiny urobil p\u00fa\u0161\u0165. Vyp\u00e1li ti mest\u00e1, \u017ee v nich neostane ani du\u0161e.",
    "8": "Preto sa odejte vrecovinou, nariekajte a kv\u00ed\u013ete, lebo bl\u010diaci hnev P\u00e1nov neodst\u00fapi od n\u00e1s.",
    "9": "I stane sa v ten de\u0148 - hovor\u00ed P\u00e1n, zmizne srdnatos\u0165 kr\u00e1\u013ea a srdnatos\u0165 knie\u017eat, st\u0155pnu k\u0148azi a zdesia sa proroci.\"",
    "10": "A bud\u00fa hovori\u0165: \"Ach, Pane, Jahve, veru si sklamal tento \u013eud a Jeruzalem, ke\u010f si vravel: \"Budete ma\u0165 pokoj;\" a h\u013ea, me\u010d vnik\u00e1 a\u017e do du\u0161e.\"",
    "11": "V tom \u010dase bud\u00fa hovori\u0165 o tomto \u013eude a o Jeruzaleme: \"Hor\u00faci vietor h\u00f4\u013e p\u00fa\u0161\u0165ou (sa r\u00fati) na dc\u00e9ru m\u00f4jho \u013eudu, nie aby vial a nie aby \u010distil.",
    "12": "Z\u00fariv\u00fd vietor mi prich\u00e1dza odtia\u013e: teraz aj ja vyhl\u00e1sim nad nimi svoj s\u00fad.\"",
    "13": "H\u013ea, dv\u00edha sa ako oblaky, jeho vozy s\u00fa s\u0165a v\u00edchrica, jeho kone s\u00fa r\u00fdchlej\u0161ie od orlov. Beda n\u00e1m, sme zni\u010den\u00ed!",
    "14": "O\u010dis\u0165 si, Jeruzalem, srdce od zloby, aby si sa zachr\u00e1nil; dokia\u013e\u017ee bud\u00fa b\u00fdva\u0165 u teba tvoje zlo\u010dinn\u00e9 my\u0161lienky?",
    "15": "Ve\u010f \u010duj! Z Danu oznamuj\u00fa a hl\u00e1sia ne\u0161\u0165astie z vrchov Efraimu.",
    "16": "Oznamujte n\u00e1rodom: \"H\u013ea, tu s\u00fa!\" Hl\u00e1ste Jeruzalemu: \"Oblieha\u010di prich\u00e1dzaj\u00fa z \u010falekej krajiny, dv\u00edhaj\u00fa svoj hlas proti mest\u00e1m J\u00fadska.",
    "17": "Obk\u013eu\u010duj\u00fa ho s\u0165a po\u013en\u00ed h\u00e1jnici, preto\u017ee mi vzdoroval,\" hovor\u00ed P\u00e1n.",
    "18": "Tvoje cesti\u010dky a tvoje skutky ti to narobili. Je to pre tvoj hriech, \u017ee je to trpk\u00e9, \u017ee ti to prenik\u00e1 a\u017e k srdcu.",
    "19": "Vn\u00fatro moje, vn\u00fatro moje, hyniem! Steny m\u00f4jho srdca! Srdce sa mi b\u00fari, nebudem ml\u010da\u0165, ve\u010f du\u0161a mi za\u010dula hlas tr\u00faby, lomoz vojnov\u00fd.",
    "20": "Skaza za skazou prask\u00e1, ve\u010f hynie cel\u00e1 krajina, v okamihu hyn\u00fa moje stany, podchv\u00ed\u013eou moje \u0161iatre.",
    "21": "Dokedy budem vidie\u0165 z\u00e1stavu, po\u010d\u00fava\u0165 zvuky tr\u00faby?",
    "22": "\"Ve\u010f m\u00f4j \u013eud je prihl\u00fapy, nepozn\u00e1va m\u0148a; s\u00fa to sprost\u00ed synovia, pochopenia nemaj\u00fa; s\u00fa m\u00fadri na zlo\u010din, a dobro robi\u0165 nevedia.\"",
    "23": "Videl som zem: h\u013ea, pust\u00e1 je a pr\u00e1zdna; a nebes\u00e1: ich svetla nebolo.",
    "24": "Videl som vrchy: h\u013ea, triasli sa a v\u0161etky pahorky sa kn\u00edsali.",
    "25": "Videl som, h\u013ea, nebolo \u010dloveka a v\u0161etky vt\u00e1\u010dky nebies uleteli.",
    "26": "Videl som, h\u013ea, sad je p\u00fa\u0161\u0165ou a v\u0161etky jeho mest\u00e1 sa zr\u00fatili pred P\u00e1nom, pred \u017eiarom jeho hnevu.",
    "27": "Lebo toto hovor\u00ed P\u00e1n: \"Spusto\u0161en\u00e1 bude cel\u00e1 krajina, ale celkom ju nezni\u010d\u00edm.",
    "28": "Pre toto bude \u017eiali\u0165 zem, tam hore s\u010dernej\u00fa nebes\u00e1, lebo som povedal a rozhodol, neobanujem a neodst\u00fapim od toho.\"",
    "29": "Pred krikom jazdcov a lukostrelcov cel\u00e9 mesto utek\u00e1, vnikli do h\u00fa\u0161tin, vyliezli na bral\u00e1. Ka\u017ed\u00e9 mesto je opusten\u00e9, neb\u00fdva v nich ani \u010dlovie\u010dik.",
    "30": "\u010co bude\u0161 robi\u0165 ty, spusto\u0161en\u00e1? Ke\u010f si purpur oblieka\u0161, ke\u010f sa ozdobuje\u0161 skvostmi zlat\u00fdmi, ke\u010f si roz\u0161iruje\u0161 o\u010di farbi\u010dkou: darmo sa kr\u00e1\u0161li\u0161, tvoji milovn\u00edci opovrhn\u00fa tebou, bud\u00fa ti siaha\u0165 na \u017eivot.",
    "31": "Ve\u010f po\u010dujem s\u0165a hlas rodi\u010dky, kv\u00edlenie ako prv\u00f4stky. Hlas dc\u00e9ry Sionu! Ston\u00e1, rozklad\u00e1 rukami: \"Ach, beda mi! Du\u0161a mi kles\u00e1 pred vrahmi.\" Trest je zasl\u00fa\u017een\u00fd"
}