{
    "1": "Toto hovor\u00ed P\u00e1n: \"Zost\u00fap do domu j\u00fadskeho kr\u00e1\u013ea a povedz tam toto slovo:",
    "2": "Povie\u0161 teda: Kr\u00e1\u013e j\u00fadsky, ktor\u00fd sed\u00ed\u0161 na D\u00e1vidovom tr\u00f3ne, po\u010duj slovo P\u00e1novo ty i tvoji sluhovia i tvoj \u013eud, ktor\u00ed vch\u00e1dzate cez tieto br\u00e1ny.",
    "3": "Toto hovor\u00ed P\u00e1n: Vysluhujte pr\u00e1vo a spravodlivos\u0165, vyslobo\u010fte utla\u010den\u00e9ho z r\u00fak n\u00e1siln\u00edka, cudzinca, sirotu a vdovu neprenasledujte a neutl\u00e1\u010dajte a nevinn\u00fa krv nevylievajte na tomto mieste.",
    "4": "Lebo ak budete bedlivo zachov\u00e1va\u0165 tento pr\u00edkaz, vtedy kr\u00e1li, ktor\u00ed sedia na D\u00e1vidovom tr\u00f3ne, bud\u00fa vch\u00e1dza\u0165 cez br\u00e1ny tohto domu, vez\u00fac sa na vozoch a na ko\u0148och, oni, ich sluhovia aj ich \u013eud.",
    "5": "Ale ak neposl\u00fachnete tieto pr\u00edkazy, prisah\u00e1m na seba - hovor\u00ed P\u00e1n, \u017ee tento dom bude zboreniskom.",
    "6": "Lebo toto hovor\u00ed P\u00e1n o dome j\u00fadskeho kr\u00e1\u013ea: Gala\u00e1dom si mi, temenom Libanonu: jednako \u0165a obr\u00e1tim na p\u00fa\u0161\u0165, na mest\u00e1 neob\u00fdvan\u00e9.",
    "7": "A zasv\u00e4t\u00edm proti tebe zhubcov, mu\u017eov s v\u00fdzbrojou. Vyr\u00fabu tvoje vyberan\u00e9 c\u00e9dre a poh\u00e1d\u017eu na ohe\u0148.",
    "8": "I prejd\u00fa mnoh\u00e9 n\u00e1rody popri tomto meste a bud\u00fa si hovori\u0165: \"Pre\u010do P\u00e1n nalo\u017eil takto s t\u00fdmto ve\u013ek\u00fdm mestom?\"",
    "9": "A odpovedia: \"Preto, \u017ee opustili zmluvu P\u00e1na, svojho Boha, kla\u0148ali sa in\u00fdm bohom a sl\u00fa\u017eili im.\"",
    "10": "Nepla\u010dte za zomrel\u00fdm a nenariekajte za n\u00edm; pla\u010dte rad\u0161ej za odch\u00e1dzaj\u00facim, preto\u017ee sa u\u017e nevr\u00e1ti a neuvid\u00ed svoj rodn\u00fd kraj.",
    "11": "Lebo toto hovor\u00ed P\u00e1n o Jozi\u00e1\u0161ovom synovi Selumovi, j\u00fadskom kr\u00e1\u013eovi, ktor\u00fd panuje namiesto svojho otca Jozi\u00e1\u0161a: \"Kto z tohto miesta odi\u0161iel, nevr\u00e1ti sa viac sem,",
    "12": "ale zomrie na mieste, kam ho odviedli, a t\u00fato krajinu u\u017e viac neuvid\u00ed.\"",
    "13": "Beda tomu, kto stavia svoj dom nespravodlivo a svoje izby nepr\u00e1vom, bezplatne si zotro\u010duje bl\u00ed\u017eneho a ned\u00e1 mu jeho mzdu;",
    "14": "kto hovor\u00ed: \"Postav\u00edm si ve\u013ek\u00fd dom a priestrann\u00e9 izby;\" vylom\u00ed si obloky, pokryje c\u00e9drom, zafarb\u00ed na \u010derveno.",
    "15": "\u010ci si kr\u00e1\u013eom, aby si sa chvastal c\u00e9drami? \u010ci tvoj otec nejedol a nepil? Ale vykon\u00e1val pr\u00e1vo a spravodlivos\u0165, a preto mu bolo dobre.",
    "16": "Rozs\u00fadil spor n\u00edzkeho a biedneho: (vtedy bolo dobre). \"\u010ci to neznamen\u00e1: pozna\u0165 m\u0148a?\" - hovor\u00ed P\u00e1n.",
    "17": "No ty nem\u00e1\u0161 o\u010di ani srdce, iba pre svoj vlastn\u00fd zisk, pre vylievanie nevinnej krvi a pre p\u00e1chanie n\u00e1silia a \u00fatlaku.",
    "18": "Preto takto hovor\u00ed P\u00e1n o Joakimovi, Jozi\u00e1\u0161ovom synovi, j\u00fadskom kr\u00e1\u013eovi: \"Nebud\u00fa za n\u00edm narieka\u0165: \"Ach brat! Ach sestra!\" Nebud\u00fa za n\u00edm narieka\u0165: \"Ach pane, ach veli\u010denstvo!\"",
    "19": "Pochovaj\u00fa ho ako osla, vyvle\u010d\u00fa ho a vyhodia von za br\u00e1ny Jeruzalema.",
    "20": "Vyst\u00fap na Libanon a kri\u010d, i na B\u00e1\u0161ane vydaj svoj hlas a volaj z Abarimu, ve\u010f s\u00fa zlomen\u00ed v\u0161etci tvoji priatelia!",
    "21": "Hovoril som ti, ke\u010f si bol v bezpe\u010d\u00ed, povedal si: \"Nechcem po\u010du\u0165!\" To je tvoj sp\u00f4sob od mladosti, nepo\u010d\u00faval si m\u00f4j hlas.",
    "22": "V\u0161etk\u00fdch tvojich pastierov bude p\u00e1s\u0165 vietor, tvoji milovn\u00edci p\u00f4jdu do zajatia; vtedy sa zahanb\u00ed\u0161 a zm\u00e4tie\u0161 pre v\u0161etku svoju zlobu.",
    "23": "Ty, ktor\u00fd b\u00fdva\u0161 na Libanone, ktor\u00fd m\u00e1\u0161 hniezdo na c\u00e9droch, bude\u0161 stena\u0165, a\u017e pr\u00eddu na teba b\u00f4le ako bolesti na rodi\u010dku.",
    "24": "\"Ako \u017eijem - hovor\u00ed P\u00e1n, aj keby j\u00fadsky kr\u00e1\u013e Choni\u00e1\u0161, syn Joakimov, bol pe\u010datn\u00fdm prste\u0148om na mojej pravici, strhol by som \u0165a odtia\u013e.",
    "25": "A vyd\u00e1m \u0165a do ruky t\u00fdch, \u010do ti striehnu na \u017eivot, do ruky t\u00fdch, ktor\u00fdch sa boj\u00ed\u0161, do ruky babylonsk\u00e9ho kr\u00e1\u013ea Nabuchodonozora a do ruky Chaldejcov.",
    "26": "A zahod\u00edm teba i matku, ktor\u00e1 \u0165a porodila, do cudzej krajiny, v ktorej ste sa nenarodili, a tam zomriete.",
    "27": "Do krajiny v\u0161ak, do ktorej sa im du\u0161a t\u00fa\u017ei vr\u00e1ti\u0165, sa nevr\u00e1tia.\"",
    "28": "\u010ci je n\u00e1dobou bezcennou, odhodenou tento mu\u017e, Choni\u00e1\u0161? \u010ci je n\u00e1dobou, ktor\u00fa nik nechce? Pre\u010do s\u00fa odvrhnut\u00ed, on a jeho sem\u00e4, zahoden\u00ed do krajiny, ktor\u00fa nepoznaj\u00fa?",
    "29": "Zem, zem, zem, po\u010duj slovo P\u00e1novo:",
    "30": "Toto hovor\u00ed P\u00e1n: \"Zap\u00ed\u0161te tohto mu\u017ea: Bezdetn\u00fd, \u010dlovek, ktor\u00fd nemal zdaru vo svojich d\u0148och, lebo z jeho potomstva sa nepodar\u00ed nikomu sedie\u0165 na D\u00e1vidovom tr\u00f3ne a znovu panova\u0165 v J\u00fadsku.\""
}