{
    "1": "Ak\u00e1 si kr\u00e1sna, priate\u013eka moja, ak\u00e1 spanil\u00e1! Tvoje o\u010di s\u00fa s\u0165a holubice za tvoj\u00edm z\u00e1vojom. Tvoje vlasy ako st\u00e1do k\u00f4z, \u010do dol' sa val\u00ed z\u00a0gala\u00e1dskych h\u00f4r.",
    "2": "Tvoje zuby ako st\u00e1do stri\u017en\u00fdch oviec, \u010do vystupuj\u00fa z k\u00fape\u013ea. Ka\u017ed\u00e1 z nich po dvoje m\u00e1 jahniatok a ani jedna nie je jalov\u00e1.",
    "3": "Tvoje pery s\u0165a purpurov\u00fd p\u00e1sik a tvoje \u00fasta pln\u00e9 p\u00f4vabu. Tvoje l\u00edca s\u0165a by kr\u00ed\u017ealky gran\u00e1tov\u00e9ho jablka za tvoj\u00edm z\u00e1vojom.",
    "4": "Tvoj krk je s\u0165a ve\u017ea D\u00e1vidova vybudovan\u00e1 s obrann\u00fdmi m\u00farikmi. Na tis\u00edc \u0161t\u00edtov vis\u00ed z nej, ve\u013ek\u00e9 to \u0161t\u00edty jun\u00e1kov.",
    "5": "Tvoje prsia s\u00fa ako dve s\u0155\u0148at\u00e1, srnie dvoj\u010diatka, ktor\u00e9 sa pas\u00fa medzi \u013ealiami.",
    "6": "A\u017e ochlad\u00ed sa de\u0148 a nach\u00fdlia sa t\u00f4ne, vyjdem si na vrch myrhov\u00fd a na kadidlov\u00fd pahor\u010dek.",
    "7": "Cel\u00e1 si kr\u00e1sna, priate\u013eka moja, a \u0161kvrny na tebe niet.",
    "8": "Po\u010f z Libanonu, nevesta moja, z Libanonu zost\u00fap! Opus\u0165 kon\u010diar Amana, vrcholce Senira a Hermona, pele\u0161e levov, vrchy leopardov.",
    "9": "O\u010darila si moje srdce, sestri\u010dka moja, nevesta, o\u010darila si moje srdce jedin\u00fdm poh\u013eadom svojich o\u010d\u00ed, jedin\u00fdm ohnivkom svojho n\u00e1hrdeln\u00edka.",
    "10": "Ak\u00e1 je sladk\u00e1 tvoja l\u00e1ska, sestri\u010dka moja, nevesta! Pr\u00edjemnej\u0161ia je tvoja l\u00e1ska nad v\u00edno. A v\u00f4\u0148a tvojich masti\u010diek je nado v\u0161etky vo\u0148avky.",
    "11": "Med z pl\u00e1sta te\u010d\u00faci s\u00fa tvoje pery, nevesta, pod tvoj\u00edm jazykom sa skr\u00fdva med a mlieko a v\u00f4\u0148a tvojich \u0161iat je s\u0165a v\u00f4\u0148a Libanonu.",
    "12": "Si zatvorenou z\u00e1hradou, sestri\u010dka moja, nevesta, si zatvorenou z\u00e1hradou, zape\u010datenou studienkou.",
    "13": "Tvoje v\u00fdhonky - to rajsk\u00fd sad gran\u00e1tovn\u00edkov s ute\u0161en\u00fdm ovoc\u00edm, s cyprusmi a nardami.",
    "14": "To nard a \u0161afran, pu\u0161kvorec a \u0161korica, so v\u0161elijakou kadidlovou krovinou; myrha a aloa, s rozli\u010dn\u00fdmi prevz\u00e1cnymi balzamy.",
    "15": "Studienka v z\u00e1hrade, \u017eriedlo \u017eiv\u00fdch v\u00f4d, \u010do z Libanonu \u017eblnkoc\u00fa.",
    "16": "Vsta\u0148, vetr\u00edk severn\u00fd! Zdvihni sa, v\u00e1nok od juhu! Prevejte moju z\u00e1hradu! Nech sa jej v\u00f4\u0148a rozn\u00e1\u0161a ...! \u00d3, keby pri\u0161iel mil\u00fd m\u00f4j do svojej z\u00e1hrady a keby po\u017e\u00edval jej znamenit\u00e9 ovocie!  V"
}