{
    "1": "Je tu (e\u0161te in\u00e9) zlo, ktor\u00e9 som videl pod slnkom a ktor\u00e9 \u0165a\u017eko (dolieha) na \u010dloveka.",
    "2": "Je to \u010dlovek, ktor\u00e9mu Boh dal bohatstvo, majetok a\u00a0sl\u00e1vu, tak\u017ee jeho du\u0161a nem\u00e1 v\u00a0ni\u010dom nedostatku,\r\n nech by si za\u017eiadal \u010doko\u013evek, ale Boh mu u\u017e nedopraje mo\u017enos\u0165, aby z\u00a0toho mohol aj po\u017e\u00edva\u0165,\r\n a niekto cudz\u00ed to po\u017eije. H\u013ea, toto je m\u00e1rnos\u0165,\r\n toto je ozaj zlostn\u00e1 choroba!",
    "3": "Keby niekto splodil aj sto synov a s\u00e1m by sa tie\u017e do\u017eil mnoho rokov, - dni jeho rokov by boli po\u010detn\u00e9 - du\u0161a by sa mu v\u0161ak nenas\u00fdtila bohatstvom, ba ani pohrebu by sa mu nedostalo: tak si (o \u0148om) mysl\u00edm, \u017ee je na tom lep\u0161ie nedoch\u00f4d\u010da ako on.",
    "4": "Lebo ono (s\u00edce) v m\u00e1rnosti pri\u0161lo (na svet) a zasa za tmy odch\u00e1dza pre\u010d: jeho meno zakr\u00fdva temno.",
    "5": "Ani slnko neuzrelo, ani ho nepoznalo, ono v\u0161ak m\u00e1 (viac) pokoja ako tamten.",
    "6": "Keby bol \u017eil tis\u00edc rokov alebo aj dvetis\u00edc, ale keby nebol ni\u010d dobr\u00e9 za\u017eil ..., \u010di nep\u00f4jde v\u0161etko na jedno a to ist\u00e9 miesto?",
    "7": "V\u0161etka n\u00e1maha \u010dloveka sl\u00fa\u017ei jeho \u00fastam - ale t\u00fdm sa jeho du\u0161a nem\u00f4\u017ee ukoji\u0165.",
    "8": "Ak\u00fa\u017ee v\u00fdhodu m\u00e1 m\u00fadry oproti pochab\u00e9mu? A \u010do bed\u00e1r, ktor\u00fd vie kr\u00e1\u010da\u0165 pred \u017eiv\u00fdmi?",
    "9": "Lep\u0161ie je o\u010dami h\u013eadie\u0165 (na dobro), ako by sa du\u0161a mala (t\u00fa\u017ebou) pomin\u00fa\u0165. Aj to je (len) m\u00e1rnos\u0165 a honba za vetrom.",
    "10": "\u010co je to, \u010doho meno u\u017e d\u00e1vno odznelo? Je zn\u00e1me, \u017ee nik sa nem\u00f4\u017ee pusti\u0165 do s\u00fadu s niek\u00fdm silnej\u0161\u00edm od seba.",
    "11": "Ve\u010f je ve\u013emi mnoho re\u010d\u00ed, ktor\u00e9 len zv\u00e4\u010d\u0161uj\u00fa m\u00e1rnos\u0165 - \u010do to m\u00f4\u017ee oso\u017ei\u0165 \u010dlovekovi?",
    "12": "Lebo kto vie, \u010do je v \u017eivote dobr\u00e9 pre \u010dloveka. Je to azda (v\u00e4\u010d\u0161\u00ed) po\u010det dn\u00ed jeho m\u00e1rneho \u017eivota, ktor\u00e9 pre\u017e\u00edva tie\u0148u podobne? Kto\u017ee vie ozn\u00e1mi\u0165 \u010dlovekovi, \u010do nastane po \u0148om pod slnkom?"
}