{
    "1": "Potom som videl z neba zostupova\u0165 in\u00e9ho anjela, ktor\u00fd m\u00e1 ve\u013ek\u00fa moc, a jeho sl\u00e1va o\u017eiarila zem.",
    "2": "Zvolal mohutn\u00fdm hlasom: \"Padol, padol ve\u013ek\u00fd Babylon a stal sa pr\u00edbytkom d\u00e9monov, skr\u00fd\u0161ou v\u0161etk\u00fdch ne\u010dist\u00fdch duchov a skr\u00fd\u0161ou ne\u010distej a odpornej zveri.",
    "3": "Lebo v\u0161etky n\u00e1rody pili z v\u00edna v\u00e1\u0161ne jeho smilstva a kr\u00e1li zeme s n\u00edm smilnili a kupci zeme zbohatli z jeho obrovsk\u00e9ho rozko\u0161n\u00edctva!\"",
    "4": "A po\u010dul som in\u00fd hlas vola\u0165 z neba: \"Vyjdite z neho, m\u00f4j \u013eud, aby ste nemali \u00fa\u010das\u0165 na jeho hriechoch a aby sa v\u00e1m nedostalo z jeho r\u00e1n,",
    "5": "lebo jeho hriechy siahaj\u00fa a\u017e po nebo a Boh sa rozpam\u00e4tal na jeho nepr\u00e1vosti.",
    "6": "Odpla\u0165te mu, ako aj on odplatil. Odpla\u0165te mu dvojn\u00e1sobne za jeho skutky. Do poh\u00e1ra, do ktor\u00e9ho nalieval, nalejte mu dvojn\u00e1sobne!",
    "7": "Ko\u013eko sa on oslavoval a h\u00fdril, to\u013eko mu dajte \u00fatrap a sm\u00fatku. Lebo si v srdci hovor\u00ed: \"Sed\u00edm ako kr\u00e1\u013eovn\u00e1, vdova nie som a sm\u00fatok neuzriem.\"",
    "8": "Preto jedn\u00e9ho d\u0148a pr\u00eddu jeho rany, smr\u0165 i sm\u00fatok a hlad a oh\u0148om bude sp\u00e1len\u00fd. Lebo mocn\u00fd je P\u00e1n Boh, ktor\u00fd ho ods\u00fadil.\"",
    "9": "I bud\u00fa nad n\u00edm plaka\u0165 a narieka\u0165 kr\u00e1li zeme, ktor\u00ed s n\u00edm smilnili a h\u00fdrili, ke\u010f uzr\u00fa dym z jeho po\u017eiaru.",
    "10": "Zastan\u00fa si ob\u010fale\u010d od hr\u00f4zy nad jeho \u00fatrapami a bud\u00fa vola\u0165: \"Beda, beda, ty ve\u013ek\u00e9 mesto Babylon, mesto tak\u00e9 mocn\u00e9, lebo v jedin\u00fa hodinu pri\u0161iel na teba s\u00fad!\"",
    "11": "Kupci zeme bud\u00fa nad n\u00edm plaka\u0165 a \u017eiali\u0165, lebo u\u017e nik nek\u00fapi ich tovar:",
    "12": "N\u00e1klad zlata a striebra, drah\u00fdch kame\u0148ov a per\u00e1l, kmentu a purpuru, hodv\u00e1bu a \u0161arl\u00e1tu, v\u0161elijak\u00e9 tujov\u00e9 drevo, v\u0161elijak\u00e9 predmety zo slonoviny, rozli\u010dn\u00e9 predmety z najvz\u00e1cnej\u0161ieho dreva, medi, \u017eeleza a mramoru;",
    "13": "\u0161koricu a balzam, vo\u0148avky a masti, kadidlo, v\u00edno a olej, m\u00faku a p\u0161enicu, dobytok a ovce, kone a vozy, otrokov a \u013eudsk\u00e9 du\u0161e.",
    "14": "A ovocie, t\u00fa\u017eba tvojej du\u0161e, odi\u0161lo od teba, v\u0161etko cenn\u00e9 a skvostn\u00e9 sa ti stratilo a u\u017e ich viac nen\u00e1jdu.",
    "15": "Kupci t\u00fdchto vec\u00ed, ktor\u00ed z neho zbohatli, zastan\u00fa si ob\u010fale\u010d od hr\u00f4zy nad jeho \u00fatrapami a bud\u00fa plaka\u0165 a \u017eiali\u0165,",
    "16": "bud\u00fa vola\u0165: \"Beda, beda, ty ve\u013ek\u00e9 mesto, ktor\u00e9 sa obliekalo do kmentu, purpuru a \u0161arl\u00e1tu a zdobilo sa zlatom, drah\u00fdmi kame\u0148mi a perlami,",
    "17": "lebo v jedin\u00fa hodinu bolo spusto\u0161en\u00e9 to\u013ek\u00e9 bohatstvo!\" V\u0161etci kormideln\u00edci a v\u0161etci, \u010do sa tadia\u013e plavili, n\u00e1morn\u00edci a v\u0161etci, \u010do pracuj\u00fa na mori, zastali ob\u010fale\u010d",
    "18": "a ke\u010f videli dym jeho po\u017eiaru, volali: \"Ktor\u00e9 mesto sa podob\u00e1 tomuto ve\u013ek\u00e9mu mestu?\"",
    "19": "Sypali si prach na hlavu a s pla\u010dom a \u017eia\u013eom volali: \"Beda, beda, ty ve\u013ek\u00e9 mesto, v ktorom zbohatli z jeho hojnosti v\u0161etci, \u010do maj\u00fa lode na mori, lebo v jedin\u00fa hodinu bolo spusto\u0161en\u00e9.",
    "20": "Plesaj nad n\u00edm, nebo a sv\u00e4t\u00ed, apo\u0161toli i proroci, lebo Boh rozs\u00fadil v\u00e1\u0161 s\u00fad na \u0148om!\"",
    "21": "Potom jeden siln\u00fd anjel vzal kame\u0148 ve\u013ek\u00fd ako \u017earnov, hodil ho do mora a zvolal: \"Takto prudko bude zvrhnut\u00fd Babylon, to ve\u013ek\u00e9 mesto, a viac ho nebude.",
    "22": "U\u017e v\u00a0tebe nebude po\u010du\u0165 hlas citaristov, hudobn\u00edkov flautistov ani po\u013enicu; u\u017e v\u00a0tebe nebude majster v\u00a0nijakom remesle ani zvuk mlyna v\u00a0tebe u\u017e viac po\u010du\u0165 nebude;",
    "23": "svetlo lampy ti u\u017e nezasvieti a\u00a0neozve sa v\u00a0tebe hlas \u017een\u00edcha a\u00a0nevesty, lebo tvoji kupci boli ve\u013emo\u017ei na zemi a\u00a0tvoje \u010dary zviedli v\u0161etky n\u00e1rody.",
    "24": "Na\u0161la sa v\u00a0\u0148om krv prorokov a\u00a0sv\u00e4t\u00fdch a\u00a0v\u0161etk\u00fdch zavra\u017eden\u00fdch na zemi!\""
}