{
    "1": "P\u00e1n hovoril Moj\u017ei\u0161ovi:",
    "2": "E\u0161te pomsti Izraelitov na Madi\u00e1n\u010danoch a potom sa pripoj\u00ed\u0161 k svojmu \u013eudu.\"",
    "3": "Vtedy Moj\u017ei\u0161 povedal svojmu \u013eudu: \"Vystrojte spomedzi seba mu\u017eov do boja, p\u00f4jdu proti Madi\u00e1n\u010danom, aby na Madi\u00e1n\u010danoch vykonali P\u00e1novu pomstu.",
    "4": "Z ka\u017ed\u00e9ho kme\u0148a po\u0161lite do boja tis\u00edc mu\u017eov, z ka\u017ed\u00e9ho Izraelovho kme\u0148a!\"",
    "5": "Takto postavili z tis\u00edcov Izraela z ka\u017ed\u00e9ho kme\u0148a jednu tis\u00edcku, teda dvan\u00e1s\u0165tis\u00edc bojovn\u00edkov.",
    "6": "A Moj\u017ei\u0161 ich poslal - jednu tis\u00edcku z ka\u017ed\u00e9ho kme\u0148a - do boja a s nimi poslal do po\u013ea Fin\u00e9sa, syna k\u0148aza Eleazara. On mal so sebou posv\u00e4tn\u00e9 veci a zvu\u010dn\u00e9 po\u013enice.",
    "7": "I tiahli proti Madi\u00e1n\u010danom, ako Moj\u017ei\u0161ovi prik\u00e1zal P\u00e1n, a pobili v\u0161etk\u00fdch mu\u017eov.",
    "8": "Medzi t\u00fdmi, ktor\u00fdch pobili, boli aj madi\u00e1nski kr\u00e1li: Evi, Rekem, Sur, Hur a Rebe, p\u00e4\u0165 madi\u00e1nskych kr\u00e1\u013eov. Aj Beorovho syna Bal\u00e1ma zabili me\u010dom.",
    "9": "Madi\u00e1nske \u017eeny a deti odviedli Izraeliti do zajatia. V\u0161etok ich dobytok, v\u0161etky ich st\u00e1da a v\u0161etok ich majetok vzali so sebou ako koris\u0165.",
    "10": "V\u0161etky ich mest\u00e1, bydlisk\u00e1 a stanov\u00e9 t\u00e1bory podp\u00e1lili.",
    "11": "Potom vzali v\u0161etku koris\u0165 a v\u0161etko, \u010doho sa zmocnili z \u013eud\u00ed i z dobytka,",
    "12": "a priviedli zajatcov aj ul\u00fapen\u00fa koris\u0165 k Moj\u017ei\u0161ovi, k\u0148azovi Eleazarovi a celej izraelskej pospolitosti do t\u00e1bora na Moabskej stepi pri Jord\u00e1ne oproti Jerichu. -",
    "13": "Moj\u017ei\u0161, k\u0148az Eleazar a v\u0161etky knie\u017eat\u00e1 \u013eudu im vy\u0161li z t\u00e1bora v \u00fastrety.",
    "14": "Moj\u017ei\u0161 sa v\u0161ak rozhneval na velite\u013eov vojsk, na vodcov, na tis\u00edcnikov a stotn\u00edkov, ktor\u00ed sa vracali z bojovej v\u00fdpravy.",
    "15": "Moj\u017ei\u0161 im vy\u010d\u00edtal: \"Pre\u010do ste nechali v\u0161etky \u017eeny na\u017eive?!",
    "16": "Ve\u010f to pr\u00e1ve ony na Bal\u00e1movu radu zviedli Izraelitov, aby kv\u00f4li Fogorovi odpadli od P\u00e1na, za \u010do stihla P\u00e1nov \u013eud n\u00e1kaza!",
    "17": "Preto teraz pobite v\u0161etk\u00fdch chlapcov a pozab\u00edjajte aj v\u0161etky \u017eeny, ktor\u00e9 u\u017e obcovali s mu\u017eom.",
    "18": "Ale v\u0161etky devy, ktor\u00e9 e\u0161te neobcovali s mu\u017eom, nechajte na\u017eive pre seba!",
    "19": "Vy ostanete sedem dn\u00ed von z t\u00e1bora. Vy v\u0161etci, ktor\u00ed ste zabili \u010dloveka alebo ste sa dotkli zabit\u00e9ho, mus\u00edte sa na tret\u00ed a siedmy de\u0148 o\u010dis\u0165ova\u0165; vy, aj va\u0161i zajatci.",
    "20": "Aj v\u0161etko \u0161atstvo, v\u0161etky ko\u017een\u00e9 veci, v\u0161etko, \u010do je zhotoven\u00e9 z kozej srsti a v\u0161etky dreven\u00e9 n\u00e1doby mus\u00edte o\u010disti\u0165.\"",
    "21": "K\u0148az Eleazar hovoril bojovn\u00edkom, ktor\u00ed sa z\u00fa\u010dastnili na vojnovej v\u00fdprave: \"Toto je z\u00e1konn\u00fd predpis, ktor\u00fd dal P\u00e1n Moj\u017ei\u0161ovi:",
    "22": "Zlato, striebro, me\u010f, \u017eelezo, olovo a c\u00edn,",
    "23": "v\u0161etko, \u010do odol\u00e1va oh\u0148u, mus\u00edte pre\u010disti\u0165 v ohni: A bude to \u010dist\u00e9; ke\u010f sa to o\u010dist\u00ed e\u0161te aj o\u010distnou vodou. Ostatn\u00e9, \u010do neodol\u00e1 oh\u0148u, mus\u00edte o\u010disti\u0165 vodou.",
    "24": "Potom na siedmy de\u0148 si vyperte \u0161atstvo a budete \u010dist\u00ed. Nato m\u00f4\u017eete pr\u00eds\u0165 do t\u00e1bora.\" -",
    "25": "P\u00e1n hovoril Moj\u017ei\u0161ovi:",
    "26": "\"Spo\u010d\u00edtaj s k\u0148azom Eleazarom a s knie\u017eatami \u013eudu v\u0161etko, \u010do sa nazbieralo ako koris\u0165 z \u013eud\u00ed a dobytka!",
    "27": "Koris\u0165 potom rozde\u013e napoly medzi t\u00fdch, \u010do sa z\u00fa\u010dastnili na boji a tiahli do po\u013ea a medzi cel\u00fa pospolitos\u0165.",
    "28": "Potom vyber od bojovn\u00edkov, \u010do tiahli do boja, d\u00e1vku pre P\u00e1na: po jednom z p\u00e4\u0165sto \u013eud\u00ed, b\u00fdkov, oslov a oviec.",
    "29": "Vezmi to z ich polovice a odovzdaj to k\u0148azovi Eleazarovi ako pozdvihovan\u00fa obetu pre P\u00e1na.",
    "30": "Z polovice, ktor\u00e1 patr\u00ed Izraelitom, odde\u013e ka\u017ed\u00e9ho p\u00e4\u0165desiateho \u010dloveka, b\u00fdka, osla, ovcu, v\u00f4bec z dobytka, a daj to levitom, ktor\u00ed konaj\u00fa slu\u017ebu pri P\u00e1novom st\u00e1nku.\"",
    "31": "A Moj\u017ei\u0161 a k\u0148az Eleazar urobili tak, ako Moj\u017ei\u0161ovi nariadil P\u00e1n.",
    "32": "Koristi, \u010di\u017ee toho, \u010do ostalo a \u010doho sa vojsko zmocnilo, bolo \u0161es\u0165stosedemdesiatp\u00e4\u0165tis\u00edc oviec (a k\u00f4z),",
    "33": "sedemdesiatdvatis\u00edc kusov hov\u00e4dzieho dobytka",
    "34": "a \u0161es\u0165desiatjedentis\u00edc oslov;",
    "35": "\u013eudsk\u00fdch du\u0161\u00ed zo \u017eien, ktor\u00e9 nepoznali obcovanie s mu\u017eom, bolo dovedna tridsa\u0165dvatis\u00edc.",
    "36": "Polovi\u010dn\u00e1 \u010diastka, ktor\u00e1 pripadla t\u00fdm, \u010do boli vo vojne, \u010dinila tristotridsa\u0165sedemtis\u00edcp\u00e4\u0165sto oviec",
    "37": "a d\u00e1vka pre P\u00e1na z oviec bola \u0161es\u0165stosedemdesiatp\u00e4\u0165 kusov,",
    "38": "\u010falej tridsa\u0165\u0161es\u0165tis\u00edc kusov hov\u00e4dzieho dobytka a d\u00e1vka z toho sedemdesiatdva kusov pre P\u00e1na,",
    "39": "k tomu tridsa\u0165tis\u00edcp\u00e4\u0165sto oslov a d\u00e1vka z toho pre P\u00e1na \u0161es\u0165desiatjeden kusov",
    "40": "a napokon \u0161estn\u00e1s\u0165tis\u00edc \u013eud\u00ed a d\u00e1vka z toho pre P\u00e1na tridsa\u0165dva du\u0161\u00ed.",
    "41": "Moj\u017ei\u0161 to odovzdal k\u0148azovi Eleazarovi ako d\u00e1vku na pozdvihovan\u00fa obetu, ako P\u00e1n prik\u00e1zal Moj\u017ei\u0161ovi.",
    "42": "V polovici, \u010do pripadla Izraelitom, ktor\u00fa Moj\u017ei\u0161 oddelil od \u010diastky bojovn\u00edkov,",
    "43": "polovici, ktor\u00e1 bola \u010diastkou pospolitosti, bolo tristotridsa\u0165sedemtis\u00edcp\u00e4\u0165sto oviec,",
    "44": "tridsa\u0165\u0161es\u0165tis\u00edc kusov hov\u00e4dzieho dobytka,",
    "45": "tridsa\u0165tis\u00edcp\u00e4\u0165sto oslov",
    "46": "a \u0161estn\u00e1s\u0165tis\u00edc \u013eud\u00ed;",
    "47": "z tejto polovice, ktor\u00e1 pripadla Izraelitom, vzal Moj\u017ei\u0161 ka\u017ed\u00e9 p\u00e4\u0165desiate z \u013eud\u00ed i z dobytka a odovzdal to levitom, ktor\u00ed konali slu\u017ebu pri P\u00e1novom st\u00e1nku, ako prik\u00e1zal P\u00e1n Moj\u017ei\u0161ovi. -",
    "48": "Tu predst\u00fapili pred Moj\u017ei\u0161a velitelia vojensk\u00fdch skup\u00edn, vodcovia tis\u00edcok a stot\u00edn",
    "49": "a povedali Moj\u017ei\u0161ovi: \"Tvoji slu\u017eobn\u00edci vykonali s\u010d\u00edtanie bojovn\u00edkov, ktor\u00ed s\u00fa pod na\u0161\u00edm velen\u00edm, a nech\u00fdba z n\u00e1s ani jeden mu\u017e.",
    "50": "Preto prin\u00e1\u0161ame - aby sme sa zbavili viny pred P\u00e1nom - ako obetn\u00fd dar pre P\u00e1na, \u010do ka\u017ed\u00fd z n\u00e1s ukoristil zo zlat\u00fdch okr\u00e1s: n\u00e1ramnice, sponky, prstene, n\u00e1u\u0161nice a n\u00e1hrdeln\u00edky.\"",
    "51": "A Moj\u017ei\u0161 i k\u0148az Eleazar prijali od nich zlato, v\u0161elijak\u00e9 umelecky zhotoven\u00e9 predmety.",
    "52": "V\u0161etk\u00e9ho zlata, ktor\u00e9 priniesli velitelia tis\u00edcok a stot\u00edn ako pozdvihovan\u00fa obetu pre P\u00e1na, bolo \u0161estn\u00e1s\u0165tis\u00edcsedemstop\u00e4\u0165desiat \u0161eklov.",
    "53": "Ale aj jednoduch\u00ed bojovn\u00edci si doniesli koris\u0165 ka\u017ed\u00fd pre seba.",
    "54": "Moj\u017ei\u0161 a k\u0148az Eleazar prevzali zlato od velite\u013eov tis\u00edcok a stot\u00edn a zaniesli ho do st\u00e1nku zjavenia, aby pripam\u00e4t\u00favalo Izraelitov u P\u00e1na."
}